pytube.py
mcbabo_pytube-0.0.1.dist-info/LICENSE
mcbabo_pytube-0.0.1.dist-info/METADATA
mcbabo_pytube-0.0.1.dist-info/WHEEL
mcbabo_pytube-0.0.1.dist-info/top_level.txt
mcbabo_pytube-0.0.1.dist-info/RECORD
