Metadata-Version: 2.1
Name: mcbabo-pytube
Version: 0.0.1
Summary: Simple Youtube API Wrapper
Home-page: https://github.com/mcbabo/pytube
Author: mcbabo
License: UNKNOWN
Platform: UNKNOWN
Classifier: Programming Language :: Python :: 3
Classifier: License :: OSI Approved :: MIT License
Classifier: Operating System :: OS Independent
Requires-Python: >=3.7
License-File: LICENSE
Requires-Dist: httpx (~=0.23)
